AUTHORS.rst
CHANGELOG.md
CONTRIBUTING.rst
LICENSE
MANIFEST.in
README.md
setup.cfg
setup.py
dogpile_filesystem/__init__.py
dogpile_filesystem/backend.py
dogpile_filesystem/locking.py
dogpile_filesystem/registry.py
dogpile_filesystem/utils.py
dogpile_filesystem.egg-info/PKG-INFO
dogpile_filesystem.egg-info/SOURCES.txt
dogpile_filesystem.egg-info/dependency_links.txt
dogpile_filesystem.egg-info/entry_points.txt
dogpile_filesystem.egg-info/not-zip-safe
dogpile_filesystem.egg-info/requires.txt
dogpile_filesystem.egg-info/top_level.txt
tests/__init__.py
tests/conftest.py
tests/test_backend.py
tests/test_locking.py