Metadata-Version: 2.1
Name: dogpile-filesystem
Version: 0.2.0
Summary: File System Backends for Dogpile Cache
Home-page: https://github.com/paylogic/dogpile_filesystem
Author: Alessio Bogon
License: MIT license
Keywords: dogpile_filesystem
Platform: UNKNOWN
Classifier: Development Status :: 4 - Beta
Classifier: Intended Audience :: Developers
Classifier: License :: OSI Approved :: MIT License
Classifier: Natural Language :: English
Classifier: Operating System :: POSIX
Classifier: Programming Language :: Python :: 2
Classifier: Programming Language :: Python :: 2.7
Classifier: Programming Language :: Python :: 3
Classifier: Programming Language :: Python :: 3.5
Classifier: Programming Language :: Python :: 3.6
Classifier: Programming Language :: Python :: 3.7
